yt_bhs/__init__.py
yt_bhs/cli.py
yt_bhs-1.0.1.dist-info/licenses/LICENSE
yt_bhs-1.0.1.dist-info/METADATA
yt_bhs-1.0.1.dist-info/WHEEL
yt_bhs-1.0.1.dist-info/entry_points.txt
yt_bhs-1.0.1.dist-info/top_level.txt
yt_bhs-1.0.1.dist-info/RECORD
