Metadata-Version: 2.4
Name: yt-bhs
Version: 1.0.1
Summary: A cmdline tool to download Youtube videos as songs through BlackHole playlists.
Author-email: neuroin <vascularsource@gmail.com>
License-Expression: Unlicense
Classifier: Environment :: Console
Classifier: Programming Language :: Python :: 3.11
Classifier: Operating System :: OS Independent
Requires-Python: >=3.11
License-File: LICENSE
Requires-Dist: yt-dlp
Requires-Dist: Pillow
Requires-Dist: mutagen
Requires-Dist: colorama
Dynamic: license-file
